autobyteus_llm_client/__init__.py
autobyteus_llm_client/cert_utils.py
autobyteus_llm_client/client.py
autobyteus_llm_client/certificates/cert.pem
tests/__init__.py
tests/conftest.py
tests/integration/__init__.py
tests/integration/test_client_integration.py
autobyteus_llm_client-1.1.3.dist-info/METADATA
autobyteus_llm_client-1.1.3.dist-info/WHEEL
autobyteus_llm_client-1.1.3.dist-info/top_level.txt
autobyteus_llm_client-1.1.3.dist-info/RECORD
