Metadata-Version: 2.4
Name: autobyteus_llm_client
Version: 1.1.3
Summary: Async Python client for Autobyteus LLM API
Home-page: https://github.com/AutoByteus/autobyteus_llm_client.git
Author: Ryan Zheng
Author-email: ryan.zheng.work@gmail.com
Keywords: llm client async
Classifier: Programming Language :: Python :: 3
Classifier: License :: OSI Approved :: MIT License
Classifier: Operating System :: OS Independent
Requires-Python: >=3.8
Requires-Dist: httpx
Requires-Dist: cryptography
Provides-Extra: test
Requires-Dist: pytest-asyncio; extra == "test"
Requires-Dist: python-dotenv; extra == "test"
Dynamic: author
Dynamic: author-email
Dynamic: classifier
Dynamic: description
Dynamic: description-content-type
Dynamic: home-page
Dynamic: keywords
Dynamic: provides-extra
Dynamic: requires-dist
Dynamic: requires-python
Dynamic: summary
